reflex_clerk_api/__init__.py
reflex_clerk_api/authentication_components.py
reflex_clerk_api/base.py
reflex_clerk_api/clerk_provider.py
reflex_clerk_api/control_components.py
reflex_clerk_api/models.py
reflex_clerk_api/organization_components.py
reflex_clerk_api/pages.py
reflex_clerk_api/unstyled_components.py
reflex_clerk_api/user_components.py
reflex_clerk_api-0.4.1.dist-info/METADATA
reflex_clerk_api-0.4.1.dist-info/WHEEL
reflex_clerk_api-0.4.1.dist-info/top_level.txt
reflex_clerk_api-0.4.1.dist-info/RECORD
