Metadata-Version: 2.4
Name: reflex-clerk-api
Version: 0.4.1
Summary: Reflex custom component wrapping @clerk/clerk-react and integrating the clerk-backend-api
Author-email: Tim Child <timjchild@gmail.com>
License-Expression: Apache-2.0
Project-URL: documentation, https://timchild.github.io/reflex-clerk-api/about/
Project-URL: repository, https://github.com/TimChild/reflex-clerk-api
Project-URL: issues, https://github.com/TimChild/reflex-clerk-api/issues
Project-URL: homepage, https://reflex-clerk-api-demo.adventuresoftim.com
Keywords: reflex,reflex-custom-components,clerk,clerk-backend-api
Classifier: Development Status :: 4 - Beta
Classifier: Typing :: Typed
Classifier: Programming Language :: Python :: 3.10
Classifier: Programming Language :: Python :: 3.11
Classifier: Programming Language :: Python :: 3.12
Classifier: Programming Language :: Python :: 3.13
Requires-Python: >=3.10
Requires-Dist: authlib<2.0.0,>=1.5.1
Requires-Dist: clerk-backend-api<3.0.0,>=2.0.0
Requires-Dist: reflex<0.8.0,>=0.7.2
Provides-Extra: dev
Requires-Dist: build; extra == "dev"
Requires-Dist: twine; extra == "dev"
